pychirp/__init__.py
pychirp/applications.py
pychirp/chirpstack.py
pychirp/device.py
pychirp/deviceProfiles.py
pychirp-0.2.5.dist-info/DESCRIPTION.rst
pychirp-0.2.5.dist-info/METADATA
pychirp-0.2.5.dist-info/RECORD
pychirp-0.2.5.dist-info/WHEEL
pychirp-0.2.5.dist-info/metadata.json
pychirp-0.2.5.dist-info/top_level.txt
